<?xml version="1.0" encoding="UTF-8"?>
<beans xmlns="http://www.springframework.org/schema/beans"
       xmlns:xsi="http://www.w3.org/2001/XMLSchema-instance"
       xsi:schemaLocation="http://www.springframework.org/schema/beans
            http://www.springframework.org/schema/beans/spring-beans.xsd">

    <bean id="user" class="cn.eccto.study.springframework.ioc.User">
        <property name="name" value="EricChen"/>
        <property name="age" value="25"/>
    </bean>

    <bean id="objectFactory" class="org.springframework.beans.factory.config.ObjectFactoryCreatingFactoryBean">
        <property name="targetBeanName" value="user"/>
    </bean>

    <bean id="superUser" class="cn.eccto.study.springframework.ioc.SuperUser">
        <property name="address" value="Shanghai"/>
    </bean>

</beans>